hic3defdr/__init__.py
hic3defdr/_version.py
hic3defdr/analysis/__init__.py
hic3defdr/analysis/alternatives.py
hic3defdr/analysis/analysis.py
hic3defdr/analysis/constructor.py
hic3defdr/analysis/core.py
hic3defdr/analysis/plotting.py
hic3defdr/analysis/simulation.py
hic3defdr/plotting/__init__.py
hic3defdr/plotting/dispersion.py
hic3defdr/plotting/distance_bias.py
hic3defdr/plotting/distance_dependence.py
hic3defdr/plotting/fdr.py
hic3defdr/plotting/fn_vs_fp.py
hic3defdr/plotting/grid.py
hic3defdr/plotting/heatmap.py
hic3defdr/plotting/histograms.py
hic3defdr/plotting/ma.py
hic3defdr/plotting/roc.py
hic3defdr/util/__init__.py
hic3defdr/util/apa.py
hic3defdr/util/balancing.py
hic3defdr/util/banded_matrix.py
hic3defdr/util/binning.py
hic3defdr/util/classification.py
hic3defdr/util/cluster_table.py
hic3defdr/util/clusters.py
hic3defdr/util/demo_data.py
hic3defdr/util/dispersion.py
hic3defdr/util/evaluation.py
hic3defdr/util/filtering.py
hic3defdr/util/logging.py
hic3defdr/util/lowess.py
hic3defdr/util/lrt.py
hic3defdr/util/matrices.py
hic3defdr/util/parallelization.py
hic3defdr/util/printing.py
hic3defdr/util/progress.py
hic3defdr/util/scaled_nb.py
hic3defdr/util/scaling.py
hic3defdr/util/simulation.py
hic3defdr/util/thresholding.py
hic3defdr-0.2.1.dist-info/LICENSE
hic3defdr-0.2.1.dist-info/METADATA
hic3defdr-0.2.1.dist-info/WHEEL
hic3defdr-0.2.1.dist-info/top_level.txt
hic3defdr-0.2.1.dist-info/RECORD
