Metadata-Version: 2.1
Name: hic3defdr
Version: 0.2.1
Summary: a genome-scale differential loop finder
Home-page: https://bitbucket.org/creminslab/hic3defdr
Author: Thomas Gilgenast
Author-email: thomasgilgenast@gmail.com
License: UNKNOWN
Platform: UNKNOWN
Classifier: Development Status :: 5 - Production/Stable
Classifier: Environment :: Console
Classifier: Intended Audience :: Science/Research
Classifier: Programming Language :: Python :: 2
Classifier: Programming Language :: Python :: 2.7
Classifier: Programming Language :: Python :: 3
Classifier: Programming Language :: Python :: 3.6
Classifier: Topic :: Scientific/Engineering :: Bio-Informatics
Classifier: License :: OSI Approved :: MIT License
Requires-Dist: numpy (>=1.14.0)
Requires-Dist: scipy (>=1.2.0)
Requires-Dist: matplotlib (>=2.1.1)
Requires-Dist: mpl-scatter-density (>=0.6)
Requires-Dist: seaborn (>=0.8.0)
Requires-Dist: pandas (>=0.21.0)
Requires-Dist: lib5c (>=0.6.0)
Requires-Dist: dill (>=0.2.9)
Requires-Dist: importlib-metadata (>=1.5.0) ; python_version < "3.8"
Provides-Extra: complete
Requires-Dist: Sphinx (>=1.8.5) ; extra == 'complete'
Requires-Dist: doctest-ignore-unicode (>=0.1.2) ; extra == 'complete'
Requires-Dist: flake8 (>=3.4.1) ; extra == 'complete'
Requires-Dist: m2r (>=0.2.1) ; extra == 'complete'
Requires-Dist: nose-exclude (>=0.5.0) ; extra == 'complete'
Requires-Dist: nose (>=1.3.7) ; extra == 'complete'
Requires-Dist: scikit-learn (>=0.20.3) ; extra == 'complete'
Requires-Dist: sphinx-rtd-theme (>=0.4.3) ; extra == 'complete'
Requires-Dist: sphinxcontrib-apidoc (>=0.3.0) ; extra == 'complete'
Requires-Dist: tqdm (>=4.32.2) ; extra == 'complete'
Provides-Extra: docs
Requires-Dist: Sphinx (>=1.8.5) ; extra == 'docs'
Requires-Dist: sphinx-rtd-theme (>=0.4.3) ; extra == 'docs'
Requires-Dist: sphinxcontrib-apidoc (>=0.3.0) ; extra == 'docs'
Requires-Dist: m2r (>=0.2.1) ; extra == 'docs'
Provides-Extra: evaluation
Requires-Dist: scikit-learn (>=0.20.3) ; extra == 'evaluation'
Provides-Extra: progress
Requires-Dist: tqdm (>=4.32.2) ; extra == 'progress'
Provides-Extra: test
Requires-Dist: nose (>=1.3.7) ; extra == 'test'
Requires-Dist: nose-exclude (>=0.5.0) ; extra == 'test'
Requires-Dist: doctest-ignore-unicode (>=0.1.2) ; extra == 'test'
Requires-Dist: flake8 (>=3.4.1) ; extra == 'test'
